_yaml/__init__.py
yaml/__init__.py
yaml/composer.py
yaml/constructor.py
yaml/cyaml.py
yaml/dumper.py
yaml/emitter.py
yaml/error.py
yaml/events.py
yaml/loader.py
yaml/nodes.py
yaml/parser.py
yaml/reader.py
yaml/representer.py
yaml/resolver.py
yaml/scanner.py
yaml/serializer.py
yaml/tokens.py
PyYAML_tabs-6.0.3.dist-info/LICENSE
PyYAML_tabs-6.0.3.dist-info/METADATA
PyYAML_tabs-6.0.3.dist-info/WHEEL
PyYAML_tabs-6.0.3.dist-info/top_level.txt
PyYAML_tabs-6.0.3.dist-info/RECORD
