Metadata-Version: 2.1
Name: PyYAML_tabs
Version: 6.0.3
Summary: YAML parser and emitter for Python with tabs indentation support
Home-page: https://pyyaml.org/
Download-URL: https://pypi.org/project/PyYAML_tabs/
Author: Kirill Simonov
Author-email: xi@resolvent.net
License: MIT
Project-URL: Bug Tracker, https://github.com/kripper/pyyaml_tabs/issues
Project-URL: CI, https://github.com/kripper/pyyaml_tabs/actions
Project-URL: Documentation, https://pyyaml.org/wiki/PyYAMLDocumentation
Project-URL: Mailing lists, http://lists.sourceforge.net/lists/listinfo/yaml-core
Project-URL: Source Code, https://github.com/kripper/pyyaml_tabs
Platform: Any
Classifier: Development Status :: 5 - Production/Stable
Classifier: Intended Audience :: Developers
Classifier: License :: OSI Approved :: MIT License
Classifier: Operating System :: OS Independent
Classifier: Programming Language :: Cython
Classifier: Programming Language :: Python
Classifier: Programming Language :: Python :: 3
Classifier: Programming Language :: Python :: 3.6
Classifier: Programming Language :: Python :: 3.7
Classifier: Programming Language :: Python :: 3.8
Classifier: Programming Language :: Python :: 3.9
Classifier: Programming Language :: Python :: 3.10
Classifier: Programming Language :: Python :: 3.11
Classifier: Programming Language :: Python :: Implementation :: CPython
Classifier: Programming Language :: Python :: Implementation :: PyPy
Classifier: Topic :: Software Development :: Libraries :: Python Modules
Classifier: Topic :: Text Processing :: Markup
Requires-Python: >=3.6
License-File: LICENSE
